pke/__init__.py
pke/base.py
pke/data_structures.py
pke/langcodes.py
pke/readers.py
pke/utils.py
pke/models/Kea-semeval2010.py2.pickle
pke/models/Kea-semeval2010.py3.pickle
pke/models/WINGNUS-semeval2010.py2.pickle
pke/models/WINGNUS-semeval2010.py3.pickle
pke/models/df-semeval2010.tsv.gz
pke/models/lda-1000-semeval2010.py2.pickle.gz
pke/models/lda-1000-semeval2010.py3.pickle.gz
pke/supervised/__init__.py
pke/supervised/api.py
pke/supervised/feature_based/__init__.py
pke/supervised/feature_based/kea.py
pke/supervised/feature_based/topiccorank.py
pke/supervised/feature_based/wingnus.py
pke/supervised/neural_based/__init__.py
pke/supervised/neural_based/seq2seq.py
pke/unsupervised/__init__.py
pke/unsupervised/graph_based/__init__.py
pke/unsupervised/graph_based/collabrank.py
pke/unsupervised/graph_based/expandrank.py
pke/unsupervised/graph_based/multipartiterank.py
pke/unsupervised/graph_based/positionrank.py
pke/unsupervised/graph_based/single_tpr.py
pke/unsupervised/graph_based/singlerank.py
pke/unsupervised/graph_based/textrank.py
pke/unsupervised/graph_based/topicrank.py
pke/unsupervised/statistical/__init__.py
pke/unsupervised/statistical/embedrank.py
pke/unsupervised/statistical/firstphrases.py
pke/unsupervised/statistical/kpminer.py
pke/unsupervised/statistical/tfidf.py
pke/unsupervised/statistical/yake.py
cogexpke-1.8.1.dist-info/LICENCE.md
cogexpke-1.8.1.dist-info/METADATA
cogexpke-1.8.1.dist-info/WHEEL
cogexpke-1.8.1.dist-info/top_level.txt
cogexpke-1.8.1.dist-info/RECORD
