Metadata-Version: 2.1
Name: cogexpke
Version: 1.8.1
Summary: Python Keyphrase Extraction module
Home-page: https://github.com/boudinfl/pke
Author: pke contributors
Author-email: j3f9y.f@gmail.com
License: gnu
Platform: UNKNOWN
License-File: LICENCE.md
Requires-Dist: six (<=1.16.0,>=1.15.0)
Requires-Dist: spacy (<=3.2.1,>=3.0.0)
Requires-Dist: nltk (==3.6.3)
Requires-Dist: networkx (<=2.6.3,>=2.4.0)
Requires-Dist: numpy (==1.16.3)
Requires-Dist: scipy (<=1.5.4,>=1.4.1)
Requires-Dist: scikit-learn (<=1.0.2,>=0.22.1)
Requires-Dist: unidecode (<=1.3.2,>=1.1.1)
Requires-Dist: future (==0.18.2)
Requires-Dist: joblib (<=1.1.0,>=0.14.1)
